keyrock_psql/__init__.py
keyrock_psql/migrator/__init__.py
keyrock_psql/migrator/migrator.py
keyrock_psql/psql/__init__.py
keyrock_psql/psql/cmd_gen.py
keyrock_psql/psql/connection.py
keyrock_psql/psql/cursor.py
keyrock_psql/psql/diff.py
keyrock_psql/psql/exc.py
keyrock_psql/psql/structure.py
keyrock_psql/psql/test_psql.py
keyrock_psql/psql/util.py
keyrock_psql-2024.2.15.1117.dist-info/METADATA
keyrock_psql-2024.2.15.1117.dist-info/WHEEL
keyrock_psql-2024.2.15.1117.dist-info/top_level.txt
keyrock_psql-2024.2.15.1117.dist-info/RECORD
